regrest/__init__.py
regrest/__main__.py
regrest/_logging.py
regrest/cli.py
regrest/config.py
regrest/decorator.py
regrest/matcher.py
regrest/storage.py
regrest-0.1.0.dist-info/licenses/LICENSE
regrest-0.1.0.dist-info/METADATA
regrest-0.1.0.dist-info/WHEEL
regrest-0.1.0.dist-info/entry_points.txt
regrest-0.1.0.dist-info/top_level.txt
regrest-0.1.0.dist-info/RECORD
