Metadata-Version: 2.4
Name: regrest
Version: 0.1.0
Summary: Regression testing tool for Python
Author-email: Katsuhiro Muto <63308909+eycjur@users.noreply.github.com>
License-Expression: MIT
Project-URL: Homepage, https://github.com/eycjur/regrest
Project-URL: Repository, https://github.com/eycjur/regrest
Project-URL: Documentation, https://github.com/eycjur/regrest#readme
Project-URL: Issues, https://github.com/eycjur/regrest/issues
Keywords: testing,regression,test,regression-testing
Classifier: Development Status :: 3 - Alpha
Classifier: Intended Audience :: Developers
Classifier: Topic :: Software Development :: Testing
Classifier: Programming Language :: Python :: 3
Classifier: Programming Language :: Python :: 3.9
Classifier: Programming Language :: Python :: 3.10
Classifier: Programming Language :: Python :: 3.11
Classifier: Programming Language :: Python :: 3.12
Classifier: Programming Language :: Python :: 3.13
Requires-Python: >=3.9
License-File: LICENSE
Requires-Dist: typer>=0.9.0
Requires-Dist: typing-extensions>=4.0.0
Provides-Extra: dev
Requires-Dist: pytest>=7.0.0; extra == "dev"
Requires-Dist: pytest-cov>=4.0.0; extra == "dev"
Requires-Dist: ruff>=0.1.0; extra == "dev"
Requires-Dist: mypy>=1.0.0; extra == "dev"
Requires-Dist: build>=1.0.0; extra == "dev"
Dynamic: license-file
